[
  {
    "line": 1,
    "elements": [
      {
        "line": 3,
        "name": "",
        "description": "",
        "type": "background",
        "keyword": "Background",
        "steps": [
          {
            "result": {
              "duration": 26789780230,
              "status": "passed"
            },
            "line": 4,
            "name": "I enter url as \"https://sports.ladbrokes.com/en-gb/\"",
            "match": {
              "arguments": [
                {
                  "val": "https://sports.ladbrokes.com/en-gb/",
                  "offset": 16
                }
              ],
              "location": "d3dregister.iEnterUrlAs(String)"
            },
            "keyword": "Given "
          }
        ]
      },
      {
        "before": [
          {
            "result": {
              "duration": 21538815289,
              "status": "passed"
            },
            "match": {
              "location": "Hooks.beforebowser()"
            }
          }
        ],
        "line": 7,
        "name": "sign in with valid details",
        "description": "",
        "id": "ladbrokes-signin;sign-in-with-valid-details",
        "after": [
          {
            "result": {
              "duration": 124975,
              "status": "passed"
            },
            "match": {
              "location": "Hooks.closebrowser()"
            }
          }
        ],
        "type": "scenario",
        "keyword": "Scenario",
        "steps": [
          {
            "result": {
              "duration": 253309296,
              "status": "passed"
            },
            "line": 8,
            "name": "I enter username as \"lilymedford\" in ladbrokes",
            "match": {
              "arguments": [
                {
                  "val": "lilymedford",
                  "offset": 21
                }
              ],
              "location": "lad_login.iEnterUsernameAsInLadbrokes(String)"
            },
            "keyword": "Given "
          },
          {
            "result": {
              "duration": 291633435,
              "status": "passed"
            },
            "line": 9,
            "name": "i enter a password as \"A1234567\" in ladbrokes",
            "match": {
              "arguments": [
                {
                  "val": "A1234567",
                  "offset": 23
                }
              ],
              "location": "lad_login.iEnterAPasswordAsInLadbrokes(String)"
            },
            "keyword": "Given "
          },
          {
            "result": {
              "duration": 251354963,
              "status": "passed"
            },
            "line": 10,
            "name": "I click login in ladborkes",
            "match": {
              "location": "lad_login.iClickLoginInLadborkes()"
            },
            "keyword": "When "
          },
          {
            "result": {
              "duration": 169537994,
              "error_message": "org.openqa.selenium.NoSuchElementException: no such element: Unable to locate element: {\"method\":\"xpath\",\"selector\":\".//*[@id\u003d\u0027header\u0027]/div/div/div/div[1]/a\"}\n  (Session info: chrome\u003d67.0.3396.99)\n  (Driver info: chromedriver\u003d2.40.565498 (ea082db3280dd6843ebfb08a625e3eb905c4f5ab),platform\u003dWindows NT 10.0.17134 x86_64) (WARNING: The server did not provide any stacktrace information)\nCommand duration or timeout: 0 milliseconds\nFor documentation on this error, please visit: http://seleniumhq.org/exceptions/no_such_element.html\nBuild info: version: \u00273.7.1\u0027, revision: \u00278a0099a\u0027, time: \u00272017-11-06T21:01:39.354Z\u0027\nSystem info: host: \u0027SUNEETBASRA\u0027, ip: \u002710.21.158.13\u0027, os.name: \u0027Windows 10\u0027, os.arch: \u0027amd64\u0027, os.version: \u002710.0\u0027, java.version: \u00271.8.0_171\u0027\nDriver info: org.openqa.selenium.chrome.ChromeDriver\nCapabilities {acceptInsecureCerts: false, acceptSslCerts: false, applicationCacheEnabled: false, browserConnectionEnabled: false, browserName: chrome, chrome: {chromedriverVersion: 2.40.565498 (ea082db3280dd6..., userDataDir: C:\\Users\\suneet\\AppData\\Loc...}, cssSelectorsEnabled: true, databaseEnabled: false, handlesAlerts: true, hasTouchScreen: false, javascriptEnabled: true, locationContextEnabled: true, mobileEmulationEnabled: false, nativeEvents: true, networkConnectionEnabled: false, pageLoadStrategy: normal, platform: XP, platformName: XP, rotatable: false, setWindowRect: true, takesHeapSnapshot: true, takesScreenshot: true, unexpectedAlertBehaviour: , unhandledPromptBehavior: , version: 67.0.3396.99, webStorageEnabled: true}\nSession ID: f6aae3afd399f58d934bfd5eda56d583\n*** Element info: {Using\u003dxpath, value\u003d.//*[@id\u003d\u0027header\u0027]/div/div/div/div[1]/a}\r\n\tat sun.reflect.NativeConstructorAccessorImpl.newInstance0(Native Method)\r\n\tat sun.reflect.NativeConstructorAccessorImpl.newInstance(NativeConstructorAccessorImpl.java:62)\r\n\tat sun.reflect.DelegatingConstructorAccessorImpl.newInstance(DelegatingConstructorAccessorImpl.java:45)\r\n\tat java.lang.reflect.Constructor.newInstance(Constructor.java:423)\r\n\tat org.openqa.selenium.remote.ErrorHandler.createThrowable(ErrorHandler.java:214)\r\n\tat org.openqa.selenium.remote.ErrorHandler.throwIfResponseFailed(ErrorHandler.java:166)\r\n\tat org.openqa.selenium.remote.http.JsonHttpResponseCodec.reconstructValue(JsonHttpResponseCodec.java:40)\r\n\tat org.openqa.selenium.remote.http.AbstractHttpResponseCodec.decode(AbstractHttpResponseCodec.java:80)\r\n\tat org.openqa.selenium.remote.http.AbstractHttpResponseCodec.decode(AbstractHttpResponseCodec.java:44)\r\n\tat org.openqa.selenium.remote.HttpCommandExecutor.execute(HttpCommandExecutor.java:164)\r\n\tat org.openqa.selenium.remote.service.DriverCommandExecutor.execute(DriverCommandExecutor.java:83)\r\n\tat org.openqa.selenium.remote.RemoteWebDriver.execute(RemoteWebDriver.java:600)\r\n\tat org.openqa.selenium.remote.RemoteWebDriver.findElement(RemoteWebDriver.java:370)\r\n\tat org.openqa.selenium.remote.RemoteWebDriver.findElementByXPath(RemoteWebDriver.java:472)\r\n\tat org.openqa.selenium.By$ByXPath.findElement(By.java:361)\r\n\tat org.openqa.selenium.remote.RemoteWebDriver.findElement(RemoteWebDriver.java:362)\r\n\tat com.QA.step_definations.lad_login.iShouldSeeInLadbrokes(lad_login.java:37)\r\n\tat ✽.Then I should see \"Deposit\" in ladbrokes(ladbrokes_signin.feature:11)\r\n",
              "status": "failed"
            },
            "line": 11,
            "name": "I should see \"Deposit\" in ladbrokes",
            "match": {
              "arguments": [
                {
                  "val": "Deposit",
                  "offset": 14
                }
              ],
              "location": "lad_login.iShouldSeeInLadbrokes(String)"
            },
            "keyword": "Then "
          }
        ],
        "tags": [
          {
            "line": 6,
            "name": "@lad_signin"
          }
        ]
      }
    ],
    "name": "ladbrokes signin",
    "description": "",
    "id": "ladbrokes-signin",
    "keyword": "Feature",
    "uri": "ladbrokes_signin.feature"
  }
]